textime/__init__.py
textime/textime.py
textime-1.0.6.dist-info/LICENSE
textime-1.0.6.dist-info/METADATA
textime-1.0.6.dist-info/WHEEL
textime-1.0.6.dist-info/top_level.txt
textime-1.0.6.dist-info/RECORD
