Metadata-Version: 2.1
Name: textime
Version: 1.0.6
Summary: Python library that converts a date written as plain text to a datetime object.
Home-page: https://github.com/Eric-Mendes/textime
Author: Eric Mendes
Author-email: ericvelasco.2000@gmail.com
License: UNKNOWN
Project-URL: Bug Tracker, https://github.com/Eric-Mendes/textime/issues
Platform: UNKNOWN
Classifier: Programming Language :: Python :: 3
Classifier: License :: OSI Approved :: MIT License
Classifier: Operating System :: OS Independent
Requires-Python: >=3.9
License-File: LICENSE
